{
  "$type": "Sungero.DataExport.ExportingObject, Sungero.DataExport",
  "FolderType": "c21fa108-1570-4155-8a0c-0d04957bc72b",
  "EntityType": null,
  "ContextType": "Folder",
  "ListViewType": "Compact",
  "EmbeddedViewType": "Card",
  "List": {
    "$type": "Sungero.NoCode.Settings.Interfaces.Models.List.ListSettings, Sungero.NoCode.Settings.Interfaces",
    "Grid": {
      "$type": "Sungero.NoCode.Settings.Interfaces.Models.List.GridSettings, Sungero.NoCode.Settings.Interfaces",
      "BaseEntityTypeGuid": "ea683a63-273e-43ae-bcf1-7a443698008a",
      "Columns": {
        "$type": "System.Collections.Generic.List`1[[Sungero.NoCode.Settings.Interfaces.Models.List.ColumnSettings, Sungero.NoCode.Settings.Interfaces]], System.Private.CoreLib",
        "$values": [
          {
            "$type": "Sungero.NoCode.Settings.Interfaces.Models.List.ColumnSettings, Sungero.NoCode.Settings.Interfaces",
            "EntityTypeGuid": "d238ef51-607e-46a5-b86a-ede4482f7f19",
            "PropertyGuid": "d7319199-3333-49cc-a7b9-8467617ccf20",
            "Width": 4.0,
            "VisibleIndex": 2,
            "IsVisible": false,
            "IsHiddenInUI": false,
            "IsRelativeWidth": true,
            "SortOrder": null
          },
          {
            "$type": "Sungero.NoCode.Settings.Interfaces.Models.List.ColumnSettings, Sungero.NoCode.Settings.Interfaces",
            "EntityTypeGuid": "d238ef51-607e-46a5-b86a-ede4482f7f19",
            "PropertyGuid": "70ebf34e-fb24-438e-9c15-20c2234e771d",
            "Width": 49.0,
            "VisibleIndex": 8,
            "IsVisible": true,
            "IsHiddenInUI": false,
            "IsRelativeWidth": true,
            "SortOrder": null
          },
          {
            "$type": "Sungero.NoCode.Settings.Interfaces.Models.List.ColumnSettings, Sungero.NoCode.Settings.Interfaces",
            "EntityTypeGuid": "d238ef51-607e-46a5-b86a-ede4482f7f19",
            "PropertyGuid": "51a65ccf-9098-46d5-a853-c9a7f7e95d28",
            "Width": 19.0,
            "VisibleIndex": 10,
            "IsVisible": true,
            "IsHiddenInUI": false,
            "IsRelativeWidth": true,
            "SortOrder": null
          },
          {
            "$type": "Sungero.NoCode.Settings.Interfaces.Models.List.ColumnSettings, Sungero.NoCode.Settings.Interfaces",
            "EntityTypeGuid": "d238ef51-607e-46a5-b86a-ede4482f7f19",
            "PropertyGuid": "4d924904-9c82-4187-ac18-b3620cf6ec87",
            "Width": 14.0,
            "VisibleIndex": 3,
            "IsVisible": false,
            "IsHiddenInUI": false,
            "IsRelativeWidth": true,
            "SortOrder": null
          },
          {
            "$type": "Sungero.NoCode.Settings.Interfaces.Models.List.ColumnSettings, Sungero.NoCode.Settings.Interfaces",
            "EntityTypeGuid": "d238ef51-607e-46a5-b86a-ede4482f7f19",
            "PropertyGuid": "dcb1774a-22e7-4e3a-987a-7691478265c8",
            "Width": 14.0,
            "VisibleIndex": 4,
            "IsVisible": false,
            "IsHiddenInUI": false,
            "IsRelativeWidth": true,
            "SortOrder": null
          },
          {
            "$type": "Sungero.NoCode.Settings.Interfaces.Models.List.ColumnSettings, Sungero.NoCode.Settings.Interfaces",
            "EntityTypeGuid": "d238ef51-607e-46a5-b86a-ede4482f7f19",
            "PropertyGuid": "93248e42-4fd7-4d99-bba7-2ddd610d1d75",
            "Width": 24.0,
            "VisibleIndex": 5,
            "IsVisible": true,
            "IsHiddenInUI": true,
            "IsRelativeWidth": false,
            "SortOrder": null
          },
          {
            "$type": "Sungero.NoCode.Settings.Interfaces.Models.List.ColumnSettings, Sungero.NoCode.Settings.Interfaces",
            "EntityTypeGuid": "d238ef51-607e-46a5-b86a-ede4482f7f19",
            "PropertyGuid": "db1786dd-6ce3-4aaa-b33f-2d82f3842fe2",
            "Width": 14.0,
            "VisibleIndex": 13,
            "IsVisible": true,
            "IsHiddenInUI": false,
            "IsRelativeWidth": true,
            "SortOrder": 1
          },
          {
            "$type": "Sungero.NoCode.Settings.Interfaces.Models.List.ColumnSettings, Sungero.NoCode.Settings.Interfaces",
            "EntityTypeGuid": "d238ef51-607e-46a5-b86a-ede4482f7f19",
            "PropertyGuid": "e305f4f0-c2ee-468b-b38f-d46a7ea0ad47",
            "Width": 14.0,
            "VisibleIndex": 14,
            "IsVisible": false,
            "IsHiddenInUI": false,
            "IsRelativeWidth": true,
            "SortOrder": null
          },
          {
            "$type": "Sungero.NoCode.Settings.Interfaces.Models.List.ColumnSettings, Sungero.NoCode.Settings.Interfaces",
            "EntityTypeGuid": "d238ef51-607e-46a5-b86a-ede4482f7f19",
            "PropertyGuid": "f8670a5a-50c8-4646-9088-e4a249a09ed0",
            "Width": 14.0,
            "VisibleIndex": 6,
            "IsVisible": false,
            "IsHiddenInUI": false,
            "IsRelativeWidth": true,
            "SortOrder": null
          },
          {
            "$type": "Sungero.NoCode.Settings.Interfaces.Models.List.ColumnSettings, Sungero.NoCode.Settings.Interfaces",
            "EntityTypeGuid": "d238ef51-607e-46a5-b86a-ede4482f7f19",
            "PropertyGuid": "93bb2c73-9d99-496a-923c-3963a086f017",
            "Width": 14.0,
            "VisibleIndex": 7,
            "IsVisible": false,
            "IsHiddenInUI": false,
            "IsRelativeWidth": true,
            "SortOrder": null
          },
          {
            "$type": "Sungero.NoCode.Settings.Interfaces.Models.List.ColumnSettings, Sungero.NoCode.Settings.Interfaces",
            "EntityTypeGuid": "d238ef51-607e-46a5-b86a-ede4482f7f19",
            "PropertyGuid": "cfdeb53d-17ff-4944-b0f6-9c60c26a7d3d",
            "Width": 24.0,
            "VisibleIndex": 9,
            "IsVisible": true,
            "IsHiddenInUI": false,
            "IsRelativeWidth": false,
            "SortOrder": null
          },
          {
            "$type": "Sungero.NoCode.Settings.Interfaces.Models.List.ColumnSettings, Sungero.NoCode.Settings.Interfaces",
            "EntityTypeGuid": "d238ef51-607e-46a5-b86a-ede4482f7f19",
            "PropertyGuid": "46569f0c-18b1-48e0-96a2-7f97215e2f2e",
            "Width": 20.0,
            "VisibleIndex": 16,
            "IsVisible": false,
            "IsHiddenInUI": false,
            "IsRelativeWidth": true,
            "SortOrder": null
          },
          {
            "$type": "Sungero.NoCode.Settings.Interfaces.Models.List.ColumnSettings, Sungero.NoCode.Settings.Interfaces",
            "EntityTypeGuid": "d238ef51-607e-46a5-b86a-ede4482f7f19",
            "PropertyGuid": "b864937c-582d-4f6f-8ceb-eecdec37e0fd",
            "Width": 10.0,
            "VisibleIndex": 17,
            "IsVisible": false,
            "IsHiddenInUI": false,
            "IsRelativeWidth": true,
            "SortOrder": null
          },
          {
            "$type": "Sungero.NoCode.Settings.Interfaces.Models.List.ColumnSettings, Sungero.NoCode.Settings.Interfaces",
            "EntityTypeGuid": "d238ef51-607e-46a5-b86a-ede4482f7f19",
            "PropertyGuid": "423fdc55-8b91-4f0c-81a6-82c71f79db49",
            "Width": 10.0,
            "VisibleIndex": 18,
            "IsVisible": false,
            "IsHiddenInUI": false,
            "IsRelativeWidth": true,
            "SortOrder": null
          },
          {
            "$type": "Sungero.NoCode.Settings.Interfaces.Models.List.ColumnSettings, Sungero.NoCode.Settings.Interfaces",
            "EntityTypeGuid": "d238ef51-607e-46a5-b86a-ede4482f7f19",
            "PropertyGuid": "3030ce66-555f-454b-9ec0-653fceb86ec4",
            "Width": 10.0,
            "VisibleIndex": 19,
            "IsVisible": false,
            "IsHiddenInUI": false,
            "IsRelativeWidth": true,
            "SortOrder": null
          },
          {
            "$type": "Sungero.NoCode.Settings.Interfaces.Models.List.ColumnSettings, Sungero.NoCode.Settings.Interfaces",
            "EntityTypeGuid": "d238ef51-607e-46a5-b86a-ede4482f7f19",
            "PropertyGuid": "11828a44-2815-45a1-8694-e4fc34351b45",
            "Width": 10.0,
            "VisibleIndex": 20,
            "IsVisible": false,
            "IsHiddenInUI": false,
            "IsRelativeWidth": true,
            "SortOrder": null
          },
          {
            "$type": "Sungero.NoCode.Settings.Interfaces.Models.List.ColumnSettings, Sungero.NoCode.Settings.Interfaces",
            "EntityTypeGuid": "d238ef51-607e-46a5-b86a-ede4482f7f19",
            "PropertyGuid": "5380ec02-41db-47eb-8c29-18704454f122",
            "Width": 14.0,
            "VisibleIndex": 12,
            "IsVisible": true,
            "IsHiddenInUI": false,
            "IsRelativeWidth": true,
            "SortOrder": null
          },
          {
            "$type": "Sungero.NoCode.Settings.Interfaces.Models.List.ColumnSettings, Sungero.NoCode.Settings.Interfaces",
            "EntityTypeGuid": "d238ef51-607e-46a5-b86a-ede4482f7f19",
            "PropertyGuid": "14fda39b-c81c-4e1c-8fc4-bf3144460f57",
            "Width": 14.0,
            "VisibleIndex": 11,
            "IsVisible": false,
            "IsHiddenInUI": false,
            "IsRelativeWidth": true,
            "SortOrder": null
          },
          {
            "$type": "Sungero.NoCode.Settings.Interfaces.Models.List.ColumnSettings, Sungero.NoCode.Settings.Interfaces",
            "EntityTypeGuid": "d238ef51-607e-46a5-b86a-ede4482f7f19",
            "PropertyGuid": "8c2dee8f-5fbf-4802-a264-c8bae0cf6617",
            "Width": 10.416666666666668,
            "VisibleIndex": 0,
            "IsVisible": false,
            "IsHiddenInUI": false,
            "IsRelativeWidth": true,
            "SortOrder": null
          },
          {
            "$type": "Sungero.NoCode.Settings.Interfaces.Models.List.ColumnSettings, Sungero.NoCode.Settings.Interfaces",
            "EntityTypeGuid": "d238ef51-607e-46a5-b86a-ede4482f7f19",
            "PropertyGuid": "fc364cc7-8a57-4c30-bc60-a29f872b4be2",
            "Width": 10.416666666666668,
            "VisibleIndex": 0,
            "IsVisible": false,
            "IsHiddenInUI": false,
            "IsRelativeWidth": true,
            "SortOrder": null
          },
          {
            "$type": "Sungero.NoCode.Settings.Interfaces.Models.List.ColumnSettings, Sungero.NoCode.Settings.Interfaces",
            "EntityTypeGuid": "d238ef51-607e-46a5-b86a-ede4482f7f19",
            "PropertyGuid": "e6a2bbf0-acd3-445e-8c5c-599b8c99f715",
            "Width": 10.416666666666668,
            "VisibleIndex": 0,
            "IsVisible": false,
            "IsHiddenInUI": false,
            "IsRelativeWidth": true,
            "SortOrder": null
          }
        ]
      }
    },
    "Filters": {
      "$type": "System.Collections.Generic.List`1[[Sungero.NoCode.Settings.Interfaces.Models.List.FilterSettings, Sungero.NoCode.Settings.Interfaces]], System.Private.CoreLib",
      "$values": [
        {
          "$type": "Sungero.NoCode.Settings.Interfaces.Models.List.FilterSettings, Sungero.NoCode.Settings.Interfaces",
          "IsVisible": true,
          "NameGuid": "9c3f497b-7435-43ac-bafd-54808bb660bc",
          "Name": null
        },
        {
          "$type": "Sungero.NoCode.Settings.Interfaces.Models.List.FilterSettings, Sungero.NoCode.Settings.Interfaces",
          "IsVisible": true,
          "NameGuid": "9c3f497b-7435-43ac-bafd-54808bb660bc",
          "Name": null
        },
        {
          "$type": "Sungero.NoCode.Settings.Interfaces.Models.List.FilterSettings, Sungero.NoCode.Settings.Interfaces",
          "IsVisible": true,
          "NameGuid": "1c364925-1fa8-4a11-9608-3b41439e535f",
          "Name": null
        },
        {
          "$type": "Sungero.NoCode.Settings.Interfaces.Models.List.FilterSettings, Sungero.NoCode.Settings.Interfaces",
          "IsVisible": true,
          "NameGuid": "2cce8ab2-8c73-41f1-86ff-b9a6628c8087",
          "Name": null
        },
        {
          "$type": "Sungero.NoCode.Settings.Interfaces.Models.List.FilterSettings, Sungero.NoCode.Settings.Interfaces",
          "IsVisible": true,
          "NameGuid": "56d3477d-60ea-46bf-b42f-0e4169daae82",
          "Name": null
        },
        {
          "$type": "Sungero.NoCode.Settings.Interfaces.Models.List.FilterSettings, Sungero.NoCode.Settings.Interfaces",
          "IsVisible": true,
          "NameGuid": "28a4b96d-3899-40dc-ab1f-4d043bf755cf",
          "Name": null
        },
        {
          "$type": "Sungero.NoCode.Settings.Interfaces.Models.List.FilterSettings, Sungero.NoCode.Settings.Interfaces",
          "IsVisible": true,
          "NameGuid": "f63464d4-fec5-4381-b450-19a886f66bfb",
          "Name": null
        },
        {
          "$type": "Sungero.NoCode.Settings.Interfaces.Models.List.FilterSettings, Sungero.NoCode.Settings.Interfaces",
          "IsVisible": true,
          "NameGuid": "f5f2d022-d805-4563-a17e-7e97fbd908e6",
          "Name": null
        },
        {
          "$type": "Sungero.NoCode.Settings.Interfaces.Models.List.FilterSettings, Sungero.NoCode.Settings.Interfaces",
          "IsVisible": true,
          "NameGuid": "01848d25-6f72-4bba-9064-b0763566eb43",
          "Name": null
        },
        {
          "$type": "Sungero.NoCode.Settings.Interfaces.Models.List.FilterSettings, Sungero.NoCode.Settings.Interfaces",
          "IsVisible": true,
          "NameGuid": "430ad03c-84f0-4153-8091-959419e728d9",
          "Name": null
        },
        {
          "$type": "Sungero.NoCode.Settings.Interfaces.Models.List.FilterSettings, Sungero.NoCode.Settings.Interfaces",
          "IsVisible": true,
          "NameGuid": "0f9d211d-466c-48fb-a4a5-dd070f48fbbc",
          "Name": null
        },
        {
          "$type": "Sungero.NoCode.Settings.Interfaces.Models.List.FilterSettings, Sungero.NoCode.Settings.Interfaces",
          "IsVisible": false,
          "NameGuid": "b77decd0-9d21-4102-be64-4aa62a50e12f",
          "Name": null
        },
        {
          "$type": "Sungero.NoCode.Settings.Interfaces.Models.List.FilterSettings, Sungero.NoCode.Settings.Interfaces",
          "IsVisible": false,
          "NameGuid": "cfb162a4-e17a-408f-af88-eeb4acec0fbd",
          "Name": null
        }
      ]
    },
    "Ribbon": {
      "$type": "Sungero.NoCode.Settings.Interfaces.Models.Entity.Ribbon.RibbonSettings, Sungero.NoCode.Settings.Interfaces",
      "Groups": {
        "$type": "System.Collections.ObjectModel.ReadOnlyCollection`1[[Sungero.NoCode.Settings.Interfaces.Models.Entity.Ribbon.RibbonSettingsGroup, Sungero.NoCode.Settings.Interfaces]], System.Private.CoreLib",
        "$values": []
      },
      "Buttons": {
        "$type": "System.Collections.ObjectModel.ReadOnlyCollection`1[[Sungero.NoCode.Settings.Interfaces.Models.Entity.Ribbon.RibbonSettingsButton, Sungero.NoCode.Settings.Interfaces]], System.Private.CoreLib",
        "$values": []
      }
    }
  },
  "Criteria": "{\"$type\":\"Sungero.NoCode.Expression.UnionExpression, Sungero.NoCode.Expression\",\"Expressions\":[{\"$type\":\"Sungero.NoCode.Expression.ConditionExpression, Sungero.NoCode.Expression\",\"LeftExpression\":{\"$type\":\"Sungero.NoCode.Expression.SimpleExpression, Sungero.NoCode.Expression\",\"Tokens\":[{\"$type\":\"Sungero.NoCode.Expression.Tokens.FunctionToken, Sungero.NoCode.Expression\",\"Name\":\"GetCurrentUser\",\"ParentTypeId\":\"32f58d8b-2a33-4eb5-813e-5cd602356b06\",\"Parameters\":[]}],\"Version\":2},\"Operator\":{\"$type\":\"Sungero.NoCode.Expression.Tokens.FunctionToken, Sungero.NoCode.Expression\",\"Name\":\"IncludedIn\",\"ParentTypeId\":\"04608308-d517-4988-93b4-4312c3ed0c4c\",\"Parameters\":[{\"$type\":\"Sungero.NoCode.Expression.Tokens.FunctionParameter, Sungero.NoCode.Expression\",\"Name\":\"value\",\"Type\":\"Sungero.Domain.Shared.IEntity, Sungero.Domain.Shared\"},{\"$type\":\"Sungero.NoCode.Expression.Tokens.FunctionParameter, Sungero.NoCode.Expression\",\"Name\":\"collection\",\"Type\":\"System.Collections.Generic.IEnumerable`1[[Sungero.Domain.Shared.IEntity, Sungero.Domain.Shared]], System.Private.CoreLib\"}]},\"RightExpression\":{\"$type\":\"Sungero.NoCode.Expression.EntityListExpression, Sungero.NoCode.Expression\",\"EntityTokens\":[{\"$type\":\"Sungero.NoCode.Expression.Tokens.EntityAdaptationToken`1[[System.Guid, System.Private.CoreLib]], Sungero.NoCode.Expression\",\"Value\":\"fc4f9d00-fc90-456f-8b55-37d325b21e6d\",\"TypeGuid\":\"5e9b55c2-c1f5-4e4f-aa09-7b6d461d87ed\"}],\"Version\":0},\"LogicalOperator\":null,\"Version\":3}],\"Version\":0}",
  "Priority": 0,
  "SettingsVersion": 2,
  "Uuid": "2d6b7e92-59c9-4cf8-8f48-2f7191307b71",
  "ModuleNameGuid": "fcc573ab-5f4e-4b20-88e8-7b1e11a7a59a",
  "StoreAsDefaultSetting": true,
  "Status": "Active"
}